nornir_salt/__init__.py
nornir_salt/plugins/__init__.py
nornir_salt/plugins/connections/__init__.py
nornir_salt/plugins/connections/ConnectionsPool.py
nornir_salt/plugins/connections/HTTPPlugin.py
nornir_salt/plugins/connections/NcclientPlugin.py
nornir_salt/plugins/connections/PureSNMPPlugin.py
nornir_salt/plugins/connections/PyATSUnicon.py
nornir_salt/plugins/connections/PyGNMIPlugin.py
nornir_salt/plugins/functions/__init__.py
nornir_salt/plugins/functions/DumpResults.py
nornir_salt/plugins/functions/FFun.py
nornir_salt/plugins/functions/HostsKeepalive.py
nornir_salt/plugins/functions/InventoryFun.py
nornir_salt/plugins/functions/ResultSerializer.py
nornir_salt/plugins/functions/TabulateFormatter.py
nornir_salt/plugins/inventory/__init__.py
nornir_salt/plugins/inventory/DictInventory.py
nornir_salt/plugins/processors/__init__.py
nornir_salt/plugins/processors/DataProcessor.py
nornir_salt/plugins/processors/DiffProcessor.py
nornir_salt/plugins/processors/NorFabEventProcessor.py
nornir_salt/plugins/processors/SaltEventProcessor.py
nornir_salt/plugins/processors/TestsProcessor.py
nornir_salt/plugins/processors/ToFileProcessor.py
nornir_salt/plugins/runners/__init__.py
nornir_salt/plugins/runners/QueueRunner.py
nornir_salt/plugins/runners/RetryRunner.py
nornir_salt/plugins/tasks/__init__.py
nornir_salt/plugins/tasks/connections.py
nornir_salt/plugins/tasks/files.py
nornir_salt/plugins/tasks/http_call.py
nornir_salt/plugins/tasks/napalm_configure.py
nornir_salt/plugins/tasks/napalm_send_commands.py
nornir_salt/plugins/tasks/ncclient_call.py
nornir_salt/plugins/tasks/netmiko_send_command_ps.py
nornir_salt/plugins/tasks/netmiko_send_commands.py
nornir_salt/plugins/tasks/netmiko_send_config.py
nornir_salt/plugins/tasks/network.py
nornir_salt/plugins/tasks/nr_test.py
nornir_salt/plugins/tasks/puresnmp_call.py
nornir_salt/plugins/tasks/pyats_genie_api.py
nornir_salt/plugins/tasks/pyats_send_commands.py
nornir_salt/plugins/tasks/pyats_send_config.py
nornir_salt-0.23.0.dist-info/entry_points.txt
nornir_salt-0.23.0.dist-info/licenses/LICENSE
nornir_salt-0.23.0.dist-info/METADATA
nornir_salt-0.23.0.dist-info/WHEEL
nornir_salt-0.23.0.dist-info/RECORD
